dustr-0.1.9.dist-info/METADATA
dustr-0.1.9.dist-info/WHEEL
dustr-0.1.9.dist-info/entry_points.txt
dustr-0.1.9.dist-info/licenses/LICENSE.txt
dustr/__init__.py
dustr/__main__.py
dustr/_dustr.cpython-313-darwin.so
dustr-0.1.9.dist-info/RECORD
