Metadata-Version: 2.4
Name: dustr
Version: 0.1.9
Classifier: Topic :: Utilities
Classifier: Programming Language :: Rust
Classifier: Programming Language :: Python :: 3
License-File: LICENSE.txt
Summary: Rust-based disk usage analyzer with histogram visualization
Author: Werner Van Geit
License-Expression: LGPL-3.0-or-later
Requires-Python: >=3.9
Project-URL: homepage, https://github.com/wvangeit/dustr
